python_tripleoclient-20.0.0.data/data/share/python-tripleoclient/templates/ephemeral-heat/heat-pod.yaml.j2
python_tripleoclient-20.0.0.data/data/share/python-tripleoclient/templates/ephemeral-heat/heat.conf.j2
tripleoclient/__init__.py
tripleoclient/command.py
tripleoclient/constants.py
tripleoclient/exceptions.py
tripleoclient/export.py
tripleoclient/heat_launcher.py
tripleoclient/plugin.py
tripleoclient/utils.py
tripleoclient/config/__init__.py
tripleoclient/config/base.py
tripleoclient/config/standalone.py
tripleoclient/config/undercloud.py
tripleoclient/tests/__init__.py
tripleoclient/tests/base.py
tripleoclient/tests/fakes.py
tripleoclient/tests/test_export.py
tripleoclient/tests/test_heat_launcher.py
tripleoclient/tests/test_overcloud_credentials.py
tripleoclient/tests/test_plugin.py
tripleoclient/tests/test_utils.py
tripleoclient/tests/config/__init__.py
tripleoclient/tests/config/test_config_base.py
tripleoclient/tests/config/test_config_standalone.py
tripleoclient/tests/config/test_config_undercloud.py
tripleoclient/tests/fixture_data/__init__.py
tripleoclient/tests/fixture_data/deployment.py
tripleoclient/tests/v1/__init__.py
tripleoclient/tests/v1/test_container_image.py
tripleoclient/tests/v1/test_overcloud_admin.py
tripleoclient/tests/v1/test_overcloud_bios.py
tripleoclient/tests/v1/test_overcloud_cell.py
tripleoclient/tests/v1/test_overcloud_export.py
tripleoclient/tests/v1/test_overcloud_export_ceph.py
tripleoclient/tests/v1/test_overcloud_parameters.py
tripleoclient/tests/v1/test_overcloud_profiles.py
tripleoclient/tests/v1/test_overcloud_raid.py
tripleoclient/tests/v1/test_plugin.py
tripleoclient/tests/v1/test_tripleo_config.py
tripleoclient/tests/v1/test_tripleo_validator.py
tripleoclient/tests/v1/baremetal/__init__.py
tripleoclient/tests/v1/baremetal/fakes.py
tripleoclient/tests/v1/overcloud_backup/__init__.py
tripleoclient/tests/v1/overcloud_backup/test_backup.py
tripleoclient/tests/v1/overcloud_config/__init__.py
python_tripleoclient-20.0.0.dist-info/AUTHORS
python_tripleoclient-20.0.0.dist-info/LICENSE
python_tripleoclient-20.0.0.dist-info/METADATA
python_tripleoclient-20.0.0.dist-info/WHEEL
python_tripleoclient-20.0.0.dist-info/entry_points.txt
python_tripleoclient-20.0.0.dist-info/pbr.json
python_tripleoclient-20.0.0.dist-info/top_level.txt
python_tripleoclient-20.0.0.dist-info/RECORD
