Metadata-Version: 2.1
Name: python-tripleoclient
Version: 20.0.0
Summary: TripleO client
Home-page: https://docs.openstack.org/python-tripleoclient/latest/
Author: OpenStack
Author-email: openstack-discuss@lists.openstack.org
License: Apache License, Version 2.0
Platform: UNKNOWN
Classifier: Environment :: Console
Classifier: Environment :: OpenStack
Classifier: Intended Audience :: Developers
Classifier: Intended Audience :: Information Technology
Classifier: Intended Audience :: System Administrators
Classifier: License :: OSI Approved :: Apache Software License
Classifier: Operating System :: OS Independent
Classifier: Programming Language :: Python
Classifier: Programming Language :: Python :: Implementation :: CPython
Classifier: Programming Language :: Python :: 3 :: Only
Classifier: Programming Language :: Python :: 3
Classifier: Programming Language :: Python :: 3.8
Classifier: Programming Language :: Python :: 3.9
Requires-Python: >=3.8
Requires-Dist: ansible-runner (>=1.4.5)
Requires-Dist: cryptography (>=2.1)
Requires-Dist: openstacksdk (>=0.48.0)
Requires-Dist: osc-lib (>=2.3.0)
Requires-Dist: pbr (!=2.1.0,>=2.0.0)
Requires-Dist: psutil (>=3.2.2)
Requires-Dist: python-heatclient (>=1.10.0)
Requires-Dist: python-ironic-inspector-client (>=1.5.0)
Requires-Dist: python-ironicclient (!=2.5.2,!=2.7.1,!=3.0.0,>=2.3.0)
Requires-Dist: python-openstackclient (>=5.2.0)
Requires-Dist: tripleo-common (>=16.3.0)
Requires-Dist: validations-libs (>=1.5.0)
